pyvhs/__init__.py
pyvhs/template_imgs/template001.png
pyvhs/template_imgs/template002.png
pyvhs/utils/__init__.py
pyvhs/utils/edits.py
pyvhs/utils/files.py
pyvhs/vhs.py
pyvhs-0.1.3.dist-info/LICENSE
pyvhs-0.1.3.dist-info/METADATA
pyvhs-0.1.3.dist-info/WHEEL
pyvhs-0.1.3.dist-info/entry_points.txt
pyvhs-0.1.3.dist-info/RECORD
