Metadata-Version: 2.1
Name: pyvhs
Version: 0.1.3
Summary: Digitized VHS Cassette Editing with Python
Home-page: https://github.com/mddunlap924/PyVHS/tree/main
License: MIT
Keywords: vhs,vcr,image processing,video
Author: Myles Dunlap
Requires-Python: >=3.8,<4.0
Classifier: License :: OSI Approved :: MIT License
Classifier: Programming Language :: Python :: 3
Classifier: Programming Language :: Python :: 3.8
Classifier: Programming Language :: Python :: 3.9
Classifier: Programming Language :: Python :: 3.10
Classifier: Programming Language :: Python :: 3.11
Requires-Dist: matplotlib (>=3.7.1,<4.0.0)
Requires-Dist: moviepy (>=1.0.3,<2.0.0)
Requires-Dist: pygame (>=2.4.0,<3.0.0)
Requires-Dist: scikit-image (>=0.21.0,<0.22.0)
Project-URL: Repository, https://github.com/mddunlap924/PyVHS/tree/main
